MANIFEST.in
README.md
descriptions.rst
requirements.txt
setup.py
mdtogh/__init__.py
mdtogh/command.py
mdtogh/github_renderer.py
mdtogh/offline_renderer.py
mdtogh/renderer.py
mdtogh/settings.py
mdtogh/toc.py
mdtogh/transform.py
mdtogh/util.py
mdtogh.egg-info/PKG-INFO
mdtogh.egg-info/SOURCES.txt
mdtogh.egg-info/dependency_links.txt
mdtogh.egg-info/entry_points.txt
mdtogh.egg-info/not-zip-safe
mdtogh.egg-info/requires.txt
mdtogh.egg-info/top_level.txt
mdtogh/templates/base.html
mdtogh/templates/content.html
mdtogh/templates/index.html
mdtogh/templates/toc.html