Metadata-Version: 1.0
Name: mdtogh
Version: 0.0.7
Summary: Transform markdown files into html with styles of github
Home-page: http://github.com/marchtea/mdtogh
Author: Summer Ruan
Author-email: marchtea213@gmail.com
License: UNKNOWN
Platform: any
